Workbook

Sheet Dashboard
A1: Branch & Recruiter Revenue Dashboard
A4: KPI | B4: Value | D4: Branch | E4: Payment Received | F4: Pending (PP + IP) | G4: Gross Billing
A5: Placements | B5: =SUM('Branch Summary'!C2:C6) -> 527 | D5: Bangalore | E5: ='Branch Summary'!E2 -> 9498397.6 | F5: ='Branch Summary'!F2+'Branch Summary'!G2 -> 8246981 | G5: ='Branch Summary'!D2 -> 17745379
A6: Recruiter Groups | B6: =SUM('Branch Summary'!B2:B6) -> 88 | D6: Delhi | E6: ='Branch Summary'!E3 -> 12563961 | F6: ='Branch Summary'!F3+'Branch Summary'!G3 -> 4928433.5 | G6: ='Branch Summary'!D3 -> 17693388
A7: Gross Billing | B7: =SUM('Branch Summary'!D2:D6) -> 53126755 | D7: Faridabad | E7: ='Branch Summary'!E4 -> 8042801.9 | F7: ='Branch Summary'!F4+'Branch Summary'!G4 -> 972160.88 | G7: ='Branch Summary'!D4 -> 9074938.8
A8: Payment Received | B8: =SUM('Branch Summary'!E2:E6) -> 35269288 | D8: Gurgaon | E8: ='Branch Summary'!E5 -> 4504175.7 | F8: ='Branch Summary'!F5+'Branch Summary'!G5 -> 3107706.7 | G8: ='Branch Summary'!D5 -> 7611882.4
A9: Pending (PP + IP) | B9: =SUM('Branch Summary'!F2:F6)+SUM('Branch Summary'!G2:G6) -> 17596498 | D9: Hyderabad | E9: ='Branch Summary'!E6 -> 659951.64 | F9: ='Branch Summary'!F6+'Branch Summary'!G6 -> 341216 | G9: ='Branch Summary'!D6 -> 1001167.6
A10: Active Revenue | B10: =SUM('Branch Summary'!K2:K6) -> 52865786
A11: Realization % | B11: =IFERROR(B8/B10,0) -> 0.66714771
A12: Records Needing Review | B12: =14 -> 14
A15: Report Notes
A16: Revenue uses Billing Amount. Branch variants Bengaluru/Banglaore are standardized to Bangalore. Blank recruiter records are retained under 'Unassigned / Blank Recruiter' so the placement total fully reconciles. Payment status 'pp' is standardized to PP. Blank Billing Amounts are excluded from revenue totals, and the invoice-like payment status value is retained as Other / Review. Original source values remain in Sorted Data.

Sheet Branch Summary
A1: Branch | B1: Recruiter Groups | C1: Placements | D1: Gross Billing | E1: Payment Received | F1: PP | G1: IP | H1: Backout | I1: Credit Note | J1: Other / Review | K1: Active Revenue | L1: Realization % | M1: Avg Revenue / Placement
A2: Gurgaon | B2: =COUNTIF('Recruiter Revenue'!$A:$A,$A2) -> 25 | C2: =SUMIF('Recruiter Revenue'!$A:$A,$A2,'Recruiter Revenue'!$D:$D) -> 166 | D2: =SUMIF('Recruiter Revenue'!$A:$A,$A2,'Recruiter Revenue'!$E:$E) -> 17745379 | E2: =SUMIF('Recruiter Revenue'!$A:$A,$A2,'Recruiter Revenue'!$F:$F) -> 9498397.6 | F2: =SUMIF('Recruiter Revenue'!$A:$A,$A2,'Recruiter Revenue'!$G:$G) -> 5245981 | G2: =SUMIF('Recruiter Revenue'!$A:$A,$A2,'Recruiter Revenue'!$H:$H) -> 3001000 | H2: =SUMIF('Recruiter Revenue'!$A:$A,$A2,'Recruiter Revenue'!$I:$I) -> 0 | I2: =SUMIF('Recruiter Revenue'!$A:$A,$A2,'Recruiter Revenue'!$J:$J) -> 0 | J2: =SUMIF('Recruiter Revenue'!$A:$A,$A2,'Recruiter Revenue'!$K:$K) -> 0 | K2: =SUMIF('Recruiter Revenue'!$A:$A,$A2,'Recruiter Revenue'!$L:$L) -> 17745379 | L2: =IFERROR(E2/K2,0) -> 0.53526035 | M2: =IFERROR(D2/C2,0) -> 106899.87
A3: Delhi | B3: =COUNTIF('Recruiter Revenue'!$A:$A,$A3) -> 16 | C3: =SUMIF('Recruiter Revenue'!$A:$A,$A3,'Recruiter Revenue'!$D:$D) -> 180 | D3: =SUMIF('Recruiter Revenue'!$A:$A,$A3,'Recruiter Revenue'!$E:$E) -> 17693388 | E3: =SUMIF('Recruiter Revenue'!$A:$A,$A3,'Recruiter Revenue'!$F:$F) -> 12563961 | F3: =SUMIF('Recruiter Revenue'!$A:$A,$A3,'Recruiter Revenue'!$G:$G) -> 3922470.7 | G3: =SUMIF('Recruiter Revenue'!$A:$A,$A3,'Recruiter Revenue'!$H:$H) -> 1005962.8 | H3: =SUMIF('Recruiter Revenue'!$A:$A,$A3,'Recruiter Revenue'!$I:$I) -> 0 | I3: =SUMIF('Recruiter Revenue'!$A:$A,$A3,'Recruiter Revenue'!$J:$J) -> 154899.5 | J3: =SUMIF('Recruiter Revenue'!$A:$A,$A3,'Recruiter Revenue'!$K:$K) -> 46094 | K3: =SUMIF('Recruiter Revenue'!$A:$A,$A3,'Recruiter Revenue'!$L:$L) -> 17492394 | L3: =IFERROR(E3/K3,0) -> 0.71825278 | M3: =IFERROR(D3/C3,0) -> 98296.599
A4: Faridabad | B4: =COUNTIF('Recruiter Revenue'!$A:$A,$A4) -> 23 | C4: =SUMIF('Recruiter Revenue'!$A:$A,$A4,'Recruiter Revenue'!$D:$D) -> 127 | D4: =SUMIF('Recruiter Revenue'!$A:$A,$A4,'Recruiter Revenue'!$E:$E) -> 9074938.8 | E4: =SUMIF('Recruiter Revenue'!$A:$A,$A4,'Recruiter Revenue'!$F:$F) -> 8042801.9 | F4: =SUMIF('Recruiter Revenue'!$A:$A,$A4,'Recruiter Revenue'!$G:$G) -> 794419.88 | G4: =SUMIF('Recruiter Revenue'!$A:$A,$A4,'Recruiter Revenue'!$H:$H) -> 177741 | H4: =SUMIF('Recruiter Revenue'!$A:$A,$A4,'Recruiter Revenue'!$I:$I) -> 0 | I4: =SUMIF('Recruiter Revenue'!$A:$A,$A4,'Recruiter Revenue'!$J:$J) -> 59976 | J4: =SUMIF('Recruiter Revenue'!$A:$A,$A4,'Recruiter Revenue'!$K:$K) -> 0 | K4: =SUMIF('Recruiter Revenue'!$A:$A,$A4,'Recruiter Revenue'!$L:$L) -> 9014962.8 | L4: =IFERROR(E4/K4,0) -> 0.89216141 | M4: =IFERROR(D4/C4,0) -> 71456.211
A5: Bangalore | B5: =COUNTIF('Recruiter Revenue'!$A:$A,$A5) -> 22 | C5: =SUMIF('Recruiter Revenue'!$A:$A,$A5,'Recruiter Revenue'!$D:$D) -> 47 | D5: =SUMIF('Recruiter Revenue'!$A:$A,$A5,'Recruiter Revenue'!$E:$E) -> 7611882.4 | E5: =SUMIF('Recruiter Revenue'!$A:$A,$A5,'Recruiter Revenue'!$F:$F) -> 4504175.7 | F5: =SUMIF('Recruiter Revenue'!$A:$A,$A5,'Recruiter Revenue'!$G:$G) -> 1931979.4 | G5: =SUMIF('Recruiter Revenue'!$A:$A,$A5,'Recruiter Revenue'!$H:$H) -> 1175727.2 | H5: =SUMIF('Recruiter Revenue'!$A:$A,$A5,'Recruiter Revenue'!$I:$I) -> 0 | I5: =SUMIF('Recruiter Revenue'!$A:$A,$A5,'Recruiter Revenue'!$J:$J) -> 0 | J5: =SUMIF('Recruiter Revenue'!$A:$A,$A5,'Recruiter Revenue'!$K:$K) -> 0 | K5: =SUMIF('Recruiter Revenue'!$A:$A,$A5,'Recruiter Revenue'!$L:$L) -> 7611882.4 | L5: =IFERROR(E5/K5,0) -> 0.59172955 | M5: =IFERROR(D5/C5,0) -> 161954.94
A6: Hyderabad | B6: =COUNTIF('Recruiter Revenue'!$A:$A,$A6) -> 2 | C6: =SUMIF('Recruiter Revenue'!$A:$A,$A6,'Recruiter Revenue'!$D:$D) -> 7 | D6: =SUMIF('Recruiter Revenue'!$A:$A,$A6,'Recruiter Revenue'!$E:$E) -> 1001167.6 | E6: =SUMIF('Recruiter Revenue'!$A:$A,$A6,'Recruiter Revenue'!$F:$F) -> 659951.64 | F6: =SUMIF('Recruiter Revenue'!$A:$A,$A6,'Recruiter Revenue'!$G:$G) -> 295401 | G6: =SUMIF('Recruiter Revenue'!$A:$A,$A6,'Recruiter Revenue'!$H:$H) -> 45815 | H6: =SUMIF('Recruiter Revenue'!$A:$A,$A6,'Recruiter Revenue'!$I:$I) -> 0 | I6: =SUMIF('Recruiter Revenue'!$A:$A,$A6,'Recruiter Revenue'!$J:$J) -> 0 | J6: =SUMIF('Recruiter Revenue'!$A:$A,$A6,'Recruiter Revenue'!$K:$K) -> 0 | K6: =SUMIF('Recruiter Revenue'!$A:$A,$A6,'Recruiter Revenue'!$L:$L) -> 1001167.6 | L6: =IFERROR(E6/K6,0) -> 0.65918195 | M6: =IFERROR(D6/C6,0) -> 143023.95
A7: TOTAL | B7: =SUM(B2:B6) -> 88 | C7: =SUM(C2:C6) -> 527 | D7: =SUM(D2:D6) -> 53126755 | E7: =SUM(E2:E6) -> 35269288 | F7: =SUM(F2:F6) -> 12190252 | G7: =SUM(G2:G6) -> 5406246 | H7: =SUM(H2:H6) -> 0 | I7: =SUM(I2:I6) -> 214875.5 | ... K7: =SUM(K2:K6) -> 52865786 | L7: =IFERROR(E7/K7,0) -> 0.66714771 | M7: =IFERROR(D7/C7,0) -> 100809.78

Sheet Recruiter Revenue
A1: Branch | B1: Account Manager | C1: Recruiter | D1: Placements | E1: Gross Billing | F1: Payment Received | G1: PP | H1: IP | I1: Backout | J1: Credit Note | K1: Other / Review | L1: Active Revenue | M1: Realization % | N1: Avg Revenue / Placement
A2: Delhi | B2: Manorma | C2: Prabhat Panchal | D2: =COUNTIFS('Sorted Data'!$C:$C,$A2,'Sorted Data'!$E:$E,$B2,'Sorted Data'!$G:$G,$C2) -> 36 | E2: =SUMIFS('Sorted Data'!$Q:$Q,'Sorted Data'!$C:$C,$A2,'Sorted Data'!$E:$E,$B2,'Sorted Data'!$G:$G,$C2) -> 3069553.2 | F2: =SUMIFS('Sorted Data'!$Q:$Q,'Sorted Data'!$C:$C,$A2,'Sorted Data'!$E:$E,$B2,'Sorted Data'!$G:$G,$C2,'Sorted Data'!$T:$T,"Payment Received") -> 2249970.8 | G2: =SUMIFS('Sorted Data'!$Q:$Q,'Sorted Data'!$C:$C,$A2,'Sorted Data'!$E:$E,$B2,'Sorted Data'!$G:$G,$C2,'Sorted Data'!$T:$T,"PP") -> 522902.4 | H2: =SUMIFS('Sorted Data'!$Q:$Q,'Sorted Data'!$C:$C,$A2,'Sorted Data'!$E:$E,$B2,'Sorted Data'!$G:$G,$C2,'Sorted Data'!$T:$T,"IP") -> 260000 | I2: =SUMIFS('Sorted Data'!$Q:$Q,'Sorted Data'!$C:$C,$A2,'Sorted Data'!$E:$E,$B2,'Sorted Data'!$G:$G,$C2,'Sorted Data'!$T:$T,"Backout") -> 0 | J2: =SUMIFS('Sorted Data'!$Q:$Q,'Sorted Data'!$C:$C,$A2,'Sorted Data'!$E:$E,$B2,'Sorted Data'!$G:$G,$C2,'Sorted Data'!$T:$T,"Credit Note") -> 36680 | K2: =SUMIFS('Sorted Data'!$Q:$Q,'Sorted Data'!$C:$C,$A2,'Sorted Data'!$E:$E,$B2,'Sorted Data'!$G:$G,$C2,'Sorted Data'!$T:$T,"Other / Review") -> 0 | L2: =F2+G2+H2 -> 3032873.2 | M2: =IFERROR(F2/L2,0) -> 0.74186115 | N2: =IFERROR(E2/D2,0) -> 85265.366
A3: Delhi | B3: Manorma | C3: Bhumika | D3: =COUNTIFS('Sorted Data'!$C:$C,$A3,'Sorted Data'!$E:$E,$B3,'Sorted Data'!$G:$G,$C3) -> 9 | E3: =SUMIFS('Sorted Data'!$Q:$Q,'Sorted Data'!$C:$C,$A3,'Sorted Data'!$E:$E,$B3,'Sorted Data'!$G:$G,$C3) -> 2722141 | F3: =SUMIFS('Sorted Data'!$Q:$Q,'Sorted Data'!$C:$C,$A3,'Sorted Data'!$E:$E,$B3,'Sorted Data'!$G:$G,$C3,'Sorted Data'!$T:$T,"Payment Received") -> 900140.96 | G3: =SUMIFS('Sorted Data'!$Q:$Q,'Sorted Data'!$C:$C,$A3,'Sorted Data'!$E:$E,$B3,'Sorted Data'!$G:$G,$C3,'Sorted Data'!$T:$T,"PP") -> 1422000 | H3: =SUMIFS('Sorted Data'!$Q:$Q,'Sorted Data'!$C:$C,$A3,'Sorted Data'!$E:$E,$B3,'Sorted Data'!$G:$G,$C3,'Sorted Data'!$T:$T,"IP") -> 400000 | I3: =SUMIFS('Sorted Data'!$Q:$Q,'Sorted Data'!$C:$C,$A3,'Sorted Data'!$E:$E,$B3,'Sorted Data'!$G:$G,$C3,'Sorted Data'!$T:$T,"Backout") -> 0 | J3: =SUMIFS('Sorted Data'!$Q:$Q,'Sorted Data'!$C:$C,$A3,'Sorted Data'!$E:$E,$B3,'Sorted Data'!$G:$G,$C3,'Sorted Data'!$T:$T,"Credit Note") -> 0 | K3: =SUMIFS('Sorted Data'!$Q:$Q,'Sorted Data'!$C:$C,$A3,'Sorted Data'!$E:$E,$B3,'Sorted Data'!$G:$G,$C3,'Sorted Data'!$T:$T,"Other / Review") -> 0 | L3: =F3+G3+H3 -> 2722141 | M3: =IFERROR(F3/L3,0) -> 0.3306739 | N3: =IFERROR(E3/D3,0) -> 302460.11
A4: Gurgaon | B4: Rohit Yadav | C4: Jatin | D4: =COUNTIFS('Sorted Data'!$C:$C,$A4,'Sorted Data'!$E:$E,$B4,'Sorted Data'!$G:$G,$C4) -> 12 | E4: =SUMIFS('Sorted Data'!$Q:$Q,'Sorted Data'!$C:$C,$A4,'Sorted Data'!$E:$E,$B4,'Sorted Data'!$G:$G,$C4) -> 2584816.7 | F4: =SUMIFS('Sorted Data'!$Q:$Q,'Sorted Data'!$C:$C,$A4,'Sorted Data'!$E:$E,$B4,'Sorted Data'!$G:$G,$C4,'Sorted Data'!$T:$T,"Payment Received") -> 1188266.8 | G4: =SUMIFS('Sorted Data'!$Q:$Q,'Sorted Data'!$C:$C,$A4,'Sorted Data'!$E:$E,$B4,'Sorted Data'!$G:$G,$C4,'Sorted Data'!$T:$T,"PP") -> 1396549.9 | H4: =SUMIFS('Sorted Data'!$Q:$Q,'Sorted Data'!$C:$C,$A4,'Sorted Data'!$E:$E,$B4,'Sorted Data'!$G:$G,$C4,'Sorted Data'!$T:$T,"IP") -> 0 | I4: =SUMIFS('Sorted Data'!$Q:$Q,'Sorted Data'!$C:$C,$A4,'Sorted Data'!$E:$E,$B4,'Sorted Data'!$G:$G,$C4,'Sorted Data'!$T:$T,"Backout") -> 0 | J4: =SUMIFS('Sorted Data'!$Q:$Q,'Sorted Data'!$C:$C,$A4,'Sorted Data'!$E:$E,$B4,'Sorted Data'!$G:$G,$C4,'Sorted Data'!$T:$T,"Credit Note") -> 0 | K4: =SUMIFS('Sorted Data'!$Q:$Q,'Sorted Data'!$C:$C,$A4,'Sorted Data'!$E:$E,$B4,'Sorted Data'!$G:$G,$C4,'Sorted Data'!$T:$T,"Other / Review") -> 0 | L4: =F4+G4+H4 -> 2584816.7 | M4: =IFERROR(F4/L4,0) -> 0.45971026 | N4: =IFERROR(E4/D4,0) -> 215401.39
A5: Gurgaon | B5: Rohit Yadav | C5: Ajit Yadav | D5: =COUNTIFS('Sorted Data'!$C:$C,$A5,'Sorted Data'!$E:$E,$B5,'Sorted Data'!$G:$G,$C5) -> 13 | E5: =SUMIFS('Sorted Data'!$Q:$Q,'Sorted Data'!$C:$C,$A5,'Sorted Data'!$E:$E,$B5,'Sorted Data'!$G:$G,$C5) -> 2469999.5 | F5: =SUMIFS('Sorted Data'!$Q:$Q,'Sorted Data'!$C:$C,$A5,'Sorted Data'!$E:$E,$B5,'Sorted Data'!$G:$G,$C5,'Sorted Data'!$T:$T,"Payment Received") -> 1243825.5 | G5: =SUMIFS('Sorted Data'!$Q:$Q,'Sorted Data'!$C:$C,$A5,'Sorted Data'!$E:$E,$B5,'Sorted Data'!$G:$G,$C5,'Sorted Data'!$T:$T,"PP") -> 1056174 | H5: =SUMIFS('Sorted Data'!$Q:$Q,'Sorted Data'!$C:$C,$A5,'Sorted Data'!$E:$E,$B5,'Sorted Data'!$G:$G,$C5,'Sorted Data'!$T:$T,"IP") -> 170000 | I5: =SUMIFS('Sorted Data'!$Q:$Q,'Sorted Data'!$C:$C,$A5,'Sorted Data'!$E:$E,$B5,'Sorted Data'!$G:$G,$C5,'Sorted Data'!$T:$T,"Backout") -> 0 | J5: =SUMIFS('Sorted Data'!$Q:$Q,'Sorted Data'!$C:$C,$A5,'Sorted Data'!$E:$E,$B5,'Sorted Data'!$G:$G,$C5,'Sorted Data'!$T:$T,"Credit Note") -> 0 | K5: =SUMIFS('Sorted Data'!$Q:$Q,'Sorted Data'!$C:$C,$A5,'Sorted Data'!$E:$E,$B5,'Sorted Data'!$G:$G,$C5,'Sorted Data'!$T:$T,"Other / Review") -> 0 | L5: =F5+G5+H5 -> 2469999.5 | M5: =IFERROR(F5/L5,0) -> 0.50357318 | N5: =IFERROR(E5/D5,0) -> 189999.96
A6: Delhi | B6: Manorma | C6: Yamini | D6: =COUNTIFS('Sorted Data'!$C:$C,$A6,'Sorted Data'!$E:$E,$B6,'Sorted Data'!$G:$G,$C6) -> 11 | E6: =SUMIFS('Sorted Data'!$Q:$Q,'Sorted Data'!$C:$C,$A6,'Sorted Data'!$E:$E,$B6,'Sorted Data'!$G:$G,$C6) -> 2163653.1 | F6: =SUMIFS('Sorted Data'!$Q:$Q,'Sorted Data'!$C:$C,$A6,'Sorted Data'!$E:$E,$B6,'Sorted Data'!$G:$G,$C6,'Sorted Data'!$T:$T,"Payment Received") -> 1560433.6 | G6: =SUMIFS('Sorted Data'!$Q:$Q,'Sorted Data'!$C:$C,$A6,'Sorted Data'!$E:$E,$B6,'Sorted Data'!$G:$G,$C6,'Sorted Data'!$T:$T,"PP") -> 527000 | H6: =SUMIFS('Sorted Data'!$Q:$Q,'Sorted Data'!$C:$C,$A6,'Sorted Data'!$E:$E,$B6,'Sorted Data'!$G:$G,$C6,'Sorted Data'!$T:$T,"IP") -> 0 | I6: =SUMIFS('Sorted Data'!$Q:$Q,'Sorted Data'!$C:$C,$A6,'Sorted Data'!$E:$E,$B6,'Sorted Data'!$G:$G,$C6,'Sorted Data'!$T:$T,"Backout") -> 0 | J6: =SUMIFS('Sorted Data'!$Q:$Q,'Sorted Data'!$C:$C,$A6,'Sorted Data'!$E:$E,$B6,'Sorted Data'!$G:$G,$C6,'Sorted Data'!$T:$T,"Credit Note") -> 76219.5 | K6: =SUMIFS('Sorted Data'!$Q:$Q,'Sorted Data'!$C:$C,$A6,'Sorted Data'!$E:$E,$B6,'Sorted Data'!$G:$G,$C6,'Sorted Data'!$T:$T,"Other / Review") -> 0 | L6: =F6+G6+H6 -> 2087433.6 | M6: =IFERROR(F6/L6,0) -> 0.74753688 | N6: =IFERROR(E6/D6,0) -> 196695.74
A7: Gurgaon | B7: Rohit Yadav | C7: Robin | D7: =COUNTIFS('Sorted Data'!$C:$C,$A7,'Sorted Data'!$E:$E,$B7,'Sorted Data'!$G:$G,$C7) -> 23 | E7: =SUMIFS('Sorted Data'!$Q:$Q,'Sorted Data'!$C:$C,$A7,'Sorted Data'!$E:$E,$B7,'Sorted Data'!$G:$G,$C7) -> 2095497.8 | F7: =SUMIFS('Sorted Data'!$Q:$Q,'Sorted Data'!$C:$C,$A7,'Sorted Data'!$E:$E,$B7,'Sorted Data'!$G:$G,$C7,'Sorted Data'!$T:$T,"Payment Received") -> 1655497.8 | G7: =SUMIFS('Sorted Data'!$Q:$Q,'Sorted Data'!$C:$C,$A7,'Sorted Data'!$E:$E,$B7,'Sorted Data'!$G:$G,$C7,'Sorted Data'!$T:$T,"PP") -> 0 | H7: =SUMIFS('Sorted Data'!$Q:$Q,'Sorted Data'!$C:$C,$A7,'Sorted Data'!$E:$E,$B7,'Sorted Data'!$G:$G,$C7,'Sorted Data'!$T:$T,"IP") -> 440000 | I7: =SUMIFS('Sorted Data'!$Q:$Q,'Sorted Data'!$C:$C,$A7,'Sorted Data'!$E:$E,$B7,'Sorted Data'!$G:$G,$C7,'Sorted Data'!$T:$T,"Backout") -> 0 | J7: =SUMIFS('Sorted Data'!$Q:$Q,'Sorted Data'!$C:$C,$A7,'Sorted Data'!$E:$E,$B7,'Sorted Data'!$G:$G,$C7,'Sorted Data'!$T:$T,"Credit Note") -> 0 | K7: =SUMIFS('Sorted Data'!$Q:$Q,'Sorted Data'!$C:$C,$A7,'Sorted Data'!$E:$E,$B7,'Sorted Data'!$G:$G,$C7,'Sorted Data'!$T:$T,"Other / Review") -> 0 | L7: =F7+G7+H7 -> 2095497.8 | M7: =IFERROR(F7/L7,0) -> 0.79002602 | N7: =IFERROR(E7/D7,0) -> 91108.598
A8: Gurgaon | B8: Rohit Yadav | C8: Priyanka | D8: =COUNTIFS('Sorted Data'!$C:$C,$A8,'Sorted Data'!$E:$E,$B8,'Sorted Data'!$G:$G,$C8) -> 24 | E8: =SUMIFS('Sorted Data'!$Q:$Q,'Sorted Data'!$C:$C,$A8,'Sorted Data'!$E:$E,$B8,'Sorted Data'!$G:$G,$C8) -> 1959613.6 | F8: =SUMIFS('Sorted Data'!$Q:$Q,'Sorted Data'!$C:$C,$A8,'Sorted Data'!$E:$E,$B8,'Sorted Data'!$G:$G,$C8,'Sorted Data'!$T:$T,"Payment Received") -> 666063.47 | G8: =SUMIFS('Sorted Data'!$Q:$Q,'Sorted Data'!$C:$C,$A8,'Sorted Data'!$E:$E,$B8,'Sorted Data'!$G:$G,$C8,'Sorted Data'!$T:$T,"PP") -> 511550.12 | H8: =SUMIFS('Sorted Data'!$Q:$Q,'Sorted Data'!$C:$C,$A8,'Sorted Data'!$E:$E,$B8,'Sorted Data'!$G:$G,$C8,'Sorted Data'!$T:$T,"IP") -> 782000 | I8: =SUMIFS('Sorted Data'!$Q:$Q,'Sorted Data'!$C:$C,$A8,'Sorted Data'!$E:$E,$B8,'Sorted Data'!$G:$G,$C8,'Sorted Data'!$T:$T,"Backout") -> 0 | J8: =SUMIFS('Sorted Data'!$Q:$Q,'Sorted Data'!$C:$C,$A8,'Sorted Data'!$E:$E,$B8,'Sorted Data'!$G:$G,$C8,'Sorted Data'!$T:$T,"Credit Note") -> 0 | K8: =SUMIFS('Sorted Data'!$Q:$Q,'Sorted Data'!$C:$C,$A8,'Sorted Data'!$E:$E,$B8,'Sorted Data'!$G:$G,$C8,'Sorted Data'!$T:$T,"Other / Review") -> 0 | L8: =F8+G8+H8 -> 1959613.6 | M8: =IFERROR(F8/L8,0) -> 0.33989531 | N8: =IFERROR(E8/D8,0) -> 81650.566
A9: Delhi | B9: Manorma | C9: Navya | D9: =COUNTIFS('Sorted Data'!$C:$C,$A9,'Sorted Data'!$E:$E,$B9,'Sorted Data'!$G:$G,$C9) -> 26 | E9: =SUMIFS('Sorted Data'!$Q:$Q,'Sorted Data'!$C:$C,$A9,'Sorted Data'!$E:$E,$B9,'Sorted Data'!$G:$G,$C9) -> 1845336.7 | F9: =SUMIFS('Sorted Data'!$Q:$Q,'Sorted Data'!$C:$C,$A9,'Sorted Data'!$E:$E,$B9,'Sorted Data'!$G:$G,$C9,'Sorted Data'!$T:$T,"Payment Received") -> 1455336.7 | G9: =SUMIFS('Sorted Data'!$Q:$Q,'Sorted Data'!$C:$C,$A9,'Sorted Data'!$E:$E,$B9,'Sorted Data'!$G:$G,$C9,'Sorted Data'!$T:$T,"PP") -> 348000 | H9: =SUMIFS('Sorted Data'!$Q:$Q,'Sorted Data'!$C:$C,$A9,'Sorted Data'!$E:$E,$B9,'Sorted Data'!$G:$G,$C9,'Sorted Data'!$T:$T,"IP") -> 0 | I9: =SUMIFS('Sorted Data'!$Q:$Q,'Sorted Data'!$C:$C,$A9,'Sorted Data'!$E:$E,$B9,'Sorted Data'!$G:$G,$C9,'Sorted Data'!$T:$T,"Backout") -> 0 | J9: =SUMIFS('Sorted Data'!$Q:$Q,'Sorted Data'!$C:$C,$A9,'Sorted Data'!$E:$E,$B9,'Sorted Data'!$G:$G,$C9,'Sorted Data'!$T:$T,"Credit Note") -> 42000 | K9: =SUMIFS('Sorted Data'!$Q:$Q,'Sorted Data'!$C:$C,$A9,'Sorted Data'!$E:$E,$B9,'Sorted Data'!$G:$G,$C9,'Sorted Data'!$T:$T,"Other / Review") -> 0 | L9: =F9+G9+H9 -> 1803336.7 | M9: =IFERROR(F9/L9,0) -> 0.80702439 | N9: =IFERROR(E9/D9,0) -> 70974.489
A10: Bangalore | B10: Jayadev | C10: Navya | D10: =COUNTIFS('Sorted Data'!$C:$C,$A10,'Sorted Data'!$E:$E,$B10,'Sorted Data'!$G:$G,$C10) -> 4 | E10: =SUMIFS('Sorted Data'!$Q:$Q,'Sorted Data'!$C:$C,$A10,'Sorted Data'!$E:$E,$B10,'Sorted Data'!$G:$G,$C10) -> 1690880 | F10: =SUMIFS('Sorted Data'!$Q:$Q,'Sorted Data'!$C:$C,$A10,'Sorted Data'!$E:$E,$B10,'Sorted Data'!$G:$G,$C10,'Sorted Data'!$T:$T,"Payment Received") -> 1024000 | G10: =SUMIFS('Sorted Data'!$Q:$Q,'Sorted Data'!$C:$C,$A10,'Sorted Data'!$E:$E,$B10,'Sorted Data'!$G:$G,$C10,'Sorted Data'!$T:$T,"PP") -> 666880 | H10: =SUMIFS('Sorted Data'!$Q:$Q,'Sorted Data'!$C:$C,$A10,'Sorted Data'!$E:$E,$B10,'Sorted Data'!$G:$G,$C10,'Sorted Data'!$T:$T,"IP") -> 0 | I10: =SUMIFS('Sorted Data'!$Q:$Q,'Sorted Data'!$C:$C,$A10,'Sorted Data'!$E:$E,$B10,'Sorted Data'!$G:$G,$C10,'Sorted Data'!$T:$T,"Backout") -> 0 | J10: =SUMIFS('Sorted Data'!$Q:$Q,'Sorted Data'!$C:$C,$A10,'Sorted Data'!$E:$E,$B10,'Sorted Data'!$G:$G,$C10,'Sorted Data'!$T:$T,"Credit Note") -> 0 | K10: =SUMIFS('Sorted Data'!$Q:$Q,'Sorted Data'!$C:$C,$A10,'Sorted Data'!$E:$E,$B10,'Sorted Data'!$G:$G,$C10,'Sorted Data'!$T:$T,"Other / Review") -> 0 | L10: =F10+G10+H10 -> 1690880 | M10: =IFERROR(F10/L10,0) -> 0.60560182 | N10: =IFERROR(E10/D10,0) -> 422720
A11: Delhi | B11: Manorma | C11: Stuti | D11: =COUNTIFS('Sorted Data'!$C:$C,$A11,'Sorted Data'!$E:$E,$B11,'Sorted Data'!$G:$G,$C11) -> 14 | E11: =SUMIFS('Sorted Data'!$Q:$Q,'Sorted Data'!$C:$C,$A11,'Sorted Data'!$E:$E,$B11,'Sorted Data'!$G:$G,$C11) -> 1541860.8 | F11: =SUMIFS('Sorted Data'!$Q:$Q,'Sorted Data'!$C:$C,$A11,'Sorted Data'!$E:$E,$B11,'Sorted Data'!$G:$G,$C11,'Sorted Data'!$T:$T,"Payment Received") -> 1390813.5 | G11: =SUMIFS('Sorted Data'!$Q:$Q,'Sorted Data'!$C:$C,$A11,'Sorted Data'!$E:$E,$B11,'Sorted Data'!$G:$G,$C11,'Sorted Data'!$T:$T,"PP") -> 104953.33 | H11: =SUMIFS('Sorted Data'!$Q:$Q,'Sorted Data'!$C:$C,$A11,'Sorted Data'!$E:$E,$B11,'Sorted Data'!$G:$G,$C11,'Sorted Data'!$T:$T,"IP") -> 0 | I11: =SUMIFS('Sorted Data'!$Q:$Q,'Sorted Data'!$C:$C,$A11,'Sorted Data'!$E:$E,$B11,'Sorted Data'!$G:$G,$C11,'Sorted Data'!$T:$T,"Backout") -> 0 | J11: =SUMIFS('Sorted Data'!$Q:$Q,'Sorted Data'!$C:$C,$A11,'Sorted Data'!$E:$E,$B11,'Sorted Data'!$G:$G,$C11,'Sorted Data'!$T:$T,"Credit Note") -> 0 | K11: =SUMIFS('Sorted Data'!$Q:$Q,'Sorted Data'!$C:$C,$A11,'Sorted Data'!$E:$E,$B11,'Sorted Data'!$G:$G,$C11,'Sorted Data'!$T:$T,"Other / Review") -> 46094 | L11: =F11+G11+H11 -> 1495766.8 | M11: =IFERROR(F11/L11,0) -> 0.92983309 | N11: =IFERROR(E11/D11,0) -> 110132.92
A12: Delhi | B12: Manorma | C12: Kavita | D12: =COUNTIFS('Sorted Data'!$C:$C,$A12,'Sorted Data'!$E:$E,$B12,'Sorted Data'!$G:$G,$C12) -> 17 | E12: =SUMIFS('Sorted Data'!$Q:$Q,'Sorted Data'!$C:$C,$A12,'Sorted Data'!$E:$E,$B12,'Sorted Data'!$G:$G,$C12) -> 1392750.5 | F12: =SUMIFS('Sorted Data'!$Q:$Q,'Sorted Data'!$C:$C,$A12,'Sorted Data'!$E:$E,$B12,'Sorted Data'!$G:$G,$C12,'Sorted Data'!$T:$T,"Payment Received") -> 1200624.5 | G12: =SUMIFS('Sorted Data'!$Q:$Q,'Sorted Data'!$C:$C,$A12,'Sorted Data'!$E:$E,$B12,'Sorted Data'!$G:$G,$C12,'Sorted Data'!$T:$T,"PP") -> 120125.93 | H12: =SUMIFS('Sorted Data'!$Q:$Q,'Sorted Data'!$C:$C,$A12,'Sorted Data'!$E:$E,$B12,'Sorted Data'!$G:$G,$C12,'Sorted Data'!$T:$T,"IP") -> 72000 | I12: =SUMIFS('Sorted Data'!$Q:$Q,'Sorted Data'!$C:$C,$A12,'Sorted Data'!$E:$E,$B12,'Sorted Data'!$G:$G,$C12,'Sorted Data'!$T:$T,"Backout") -> 0 | J12: =SUMIFS('Sorted Data'!$Q:$Q,'Sorted Data'!$C:$C,$A12,'Sorted Data'!$E:$E,$B12,'Sorted Data'!$G:$G,$C12,'Sorted Data'!$T:$T,"Credit Note") -> 0 | K12: =SUMIFS('Sorted Data'!$Q:$Q,'Sorted Data'!$C:$C,$A12,'Sorted Data'!$E:$E,$B12,'Sorted Data'!$G:$G,$C12,'Sorted Data'!$T:$T,"Other / Review") -> 0 | L12: =F12+G12+H12 -> 1392750.5 | M12: =IFERROR(F12/L12,0) -> 0.86205287 | N12: =IFERROR(E12/D12,0) -> 81926.498
A13: Bangalore | B13: Avinash | C13: Rakshita | D13: =COUNTIFS('Sorted Data'!$C:$C,$A13,'Sorted Data'!$E:$E,$B13,'Sorted Data'!$G:$G,$C13) -> 7 | E13: =SUMIFS('Sorted Data'!$Q:$Q,'Sorted Data'!$C:$C,$A13,'Sorted Data'!$E:$E,$B13,'Sorted Data'!$G:$G,$C13) -> 1368610.1 | F13: =SUMIFS('Sorted Data'!$Q:$Q,'Sorted Data'!$C:$C,$A13,'Sorted Data'!$E:$E,$B13,'Sorted Data'!$G:$G,$C13,'Sorted Data'!$T:$T,"Payment Received") -> 1029418.8 | G13: =SUMIFS('Sorted Data'!$Q:$Q,'Sorted Data'!$C:$C,$A13,'Sorted Data'!$E:$E,$B13,'Sorted Data'!$G:$G,$C13,'Sorted Data'!$T:$T,"PP") -> 33320 | H13: =SUMIFS('Sorted Data'!$Q:$Q,'Sorted Data'!$C:$C,$A13,'Sorted Data'!$E:$E,$B13,'Sorted Data'!$G:$G,$C13,'Sorted Data'!$T:$T,"IP") -> 305871.34 | I13: =SUMIFS('Sorted Data'!$Q:$Q,'Sorted Data'!$C:$C,$A13,'Sorted Data'!$E:$E,$B13,'Sorted Data'!$G:$G,$C13,'Sorted Data'!$T:$T,"Backout") -> 0 | J13: =SUMIFS('Sorted Data'!$Q:$Q,'Sorted Data'!$C:$C,$A13,'Sorted Data'!$E:$E,$B13,'Sorted Data'!$G:$G,$C13,'Sorted Data'!$T:$T,"Credit Note") -> 0 | K13: =SUMIFS('Sorted Data'!$Q:$Q,'Sorted Data'!$C:$C,$A13,'Sorted Data'!$E:$E,$B13,'Sorted Data'!$G:$G,$C13,'Sorted Data'!$T:$T,"Other / Review") -> 0 | L13: =F13+G13+H13 -> 1368610.1 | M13: =IFERROR(F13/L13,0) -> 0.75216365 | N13: =IFERROR(E13/D13,0) -> 195515.73
... A89: Gurgaon | B89: Rohit Yadav | C89: Priyanaka | D89: =COUNTIFS('Sorted Data'!$C:$C,$A89,'Sorted Data'!$E:$E,$B89,'Sorted Data'!$G:$G,$C89) -> 1 | E89: =SUMIFS('Sorted Data'!$Q:$Q,'Sorted Data'!$C:$C,$A89,'Sorted Data'!$E:$E,$B89,'Sorted Data'!$G:$G,$C89) -> 0 | F89: =SUMIFS('Sorted Data'!$Q:$Q,'Sorted Data'!$C:$C,$A89,'Sorted Data'!$E:$E,$B89,'Sorted Data'!$G:$G,$C89,'Sorted Data'!$T:$T,"Payment Received") -> 0 | G89: =SUMIFS('Sorted Data'!$Q:$Q,'Sorted Data'!$C:$C,$A89,'Sorted Data'!$E:$E,$B89,'Sorted Data'!$G:$G,$C89,'Sorted Data'!$T:$T,"PP") -> 0 | H89: =SUMIFS('Sorted Data'!$Q:$Q,'Sorted Data'!$C:$C,$A89,'Sorted Data'!$E:$E,$B89,'Sorted Data'!$G:$G,$C89,'Sorted Data'!$T:$T,"IP") -> 0 | I89: =SUMIFS('Sorted Data'!$Q:$Q,'Sorted Data'!$C:$C,$A89,'Sorted Data'!$E:$E,$B89,'Sorted Data'!$G:$G,$C89,'Sorted Data'!$T:$T,"Backout") -> 0 | J89: =SUMIFS('Sorted Data'!$Q:$Q,'Sorted Data'!$C:$C,$A89,'Sorted Data'!$E:$E,$B89,'Sorted Data'!$G:$G,$C89,'Sorted Data'!$T:$T,"Credit Note") -> 0 | K89: =SUMIFS('Sorted Data'!$Q:$Q,'Sorted Data'!$C:$C,$A89,'Sorted Data'!$E:$E,$B89,'Sorted Data'!$G:$G,$C89,'Sorted Data'!$T:$T,"Other / Review") -> 0 | L89: =F89+G89+H89 -> 0 | M89: =IFERROR(F89/L89,0) -> 0 | N89: =IFERROR(E89/D89,0) -> 0

Sheet Sorted Data
A1: S.No | B1: Branch (Original) | C1: Branch (Standard) | D1: Account Manager (Original) | E1: Account Manager (Standard) | F1: Recruiter (Original) | G1: Recruiter (Standard) | H1: Organization | I1: Candidate Name | J1: Designation | K1: Department | L1: Location | M1: DOJ | N1: Offered CTC | O1: Invoice No. | P1: Billing Amount (Original) | Q1: Revenue (Numeric) | R1: Invoice Date | S1: Payment Status (Original) | T1: Payment Status (Standard) | U1: Data Quality Note
A2: 3538 | B2: Banglaore | C2: Bangalore | D2: Avinash | E2: Avinash | F2: Ajit / Avinash | G2: Ajit / Avinash | H2: Royal Enfield | I2: Priyadarshan | J2: Paint R&D | L2: Chennai | M2: 09.09.26 | N2: 1120000 | O2: Joined | P2: 23324 | Q2: 23324 | S2: IP | T2: IP | U2: Branch normalized: Banglaore → Bangalore
A3: 3420 | B3: Bengaluru | C3: Bangalore | D3: Avinash | E3: Avinash | F3: Jayadev | G3: Jayadev | H3: Mahindra AI | I3: Shivam S | J3: Sr. Data Science | L3: Bengaluru | M3: 16.07.26 | N3: 31,45,006 | O3: VHCPL/26-27/46 | P3: 3,14,500.60 | Q3: 314500.6 | R3: 30.7.2026 | S3: PP | T3: PP | U3: Branch normalized: Bengaluru → Bangalore
A4: 3012 | B4: Bangalore | C4: Bangalore | D4: Avinash | E4: Avinash | F4: Jayadev | G4: Jayadev | H4: Miebach | I4: Tejeshwar | J4: PM | L4: Mumbai | M4: 05.1.26 | N4: 4402000 | O4: VHCPL/25-26/102 | P4: 528240 | Q4: 528240 | R4: 13.02.2026 | S4: Payment Received | T4: Payment Received
A5: 3518 | B5: Bangalore | C5: Bangalore | D5: Avinash | E5: Avinash | F5: Lalitha Sri | G5: Lalitha Sri | H5: Royal Enfield | I5: Ahamed Basha | J5: Store & Warehouse | L5: Chennai | M5: 07.09.26 | N5: 4,00,000 | O5: PI/26-27/80 | P5: 33320 | Q5: 33320 | R5: 16.9.2026 | S5: IP | T5: IP
A6: 3517 | B6: Bangalore | C6: Bangalore | D6: Avinash | E6: Avinash | F6: Lalitha Sri | G6: Lalitha Sri | H6: Royal Enfield | I6: Parthiban P | J6: Store & Warehouse | L6: Chennai | M6: 07.09.26 | N6: 4,50,000 | O6: PI/26-27/80 | P6: 37485 | Q6: 37485 | R6: 16.9.2026 | S6: IP | T6: IP
A7: 3024 | B7: Bangalore | C7: Bangalore | D7: Avinash | E7: Avinash | F7: Navya | G7: Navya | H7: Best Auto | I7: Abhishek Jain | J7: Design Engineer | L7: Bilaspur | M7: 16.01.26 | N7: 516000 | O7: VHCPL/25-26/99 | P7: 42982.8 | Q7: 42982.8 | R7: 07.02.2026 | S7: Payment Received | T7: Payment Received
A8: 3519 | B8: Bengaluru | C8: Bangalore | D8: Avinash | E8: Avinash | F8: Navya | G8: Navya | H8: BFW | I8: Amol Pawar | J8: HR Business Partner (HR BP) - Sales, Marketing & Post-Sales | L8: Pune | M8: 07.09.26 | N8: 1400000 | O8: Joined | P8: 116620 | Q8: 116620 | S8: IP | T8: IP | U8: Branch normalized: Bengaluru → Bangalore
A9: 3421 | B9: Bengaluru | C9: Bangalore | D9: Avinash | E9: Avinash | F9: Navya | G9: Navya | H9: Royal Enfield | I9: Muralidharan G | J9: SE - MSE - Fabrication | L9: Chennai | M9: 20.07.26 | N9: 750000 | O9: VHCPL/26-27/81 | P9: 62475 | Q9: 62475 | R9: 17.9.2026 | S9: PP | T9: PP | U9: Branch normalized: Bengaluru → Bangalore
A10: 3462 | B10: Bangalore | C10: Bangalore | D10: Avinash | E10: Avinash | F10: Navya | G10: Navya | H10: Royal Enfield | I10: Vignesh.S | J10: Liquid Painting | L10: Chennai | M10: 17.08.26 | N10: 16,01,786 | O10: PI/26-27/79 | P10: 1,33,428.77 | Q10: 133428.77 | R10: 16.9.2026 | S10: IP | T10: IP
A11: 3205 | B11: Bangalore | C11: Bangalore | D11: Avinash | E11: Avinash | F11: Rakshita | G11: Rakshita | H11: Carraro | I11: Suyog Mashelkar | J11: Quality Head | L11: Pune | M11: 13.04.26 | N11: 4500000 | O11: VHC/26-27/31 | P11: 470285 | Q11: 470285 | R11: 13.5-2026 | S11: Payment Received | T11: Payment Received
A12: 3207 | B12: Bangalore | C12: Bangalore | D12: Avinash | E12: Avinash | F12: Rakshita | G12: Rakshita | H12: Miebach | I12: Saurav Kumar | J12: Sr. Consultant | L12: Gurgaon | M12: 13.04.26 | N12: 2900000 | O12: VHCPL/26-27/13 | P12: 290000 | Q12: 290000 | R12: 15.05.26 | S12: Payment Received | T12: Payment Received
A13: 3430 | B13: Banglaore | C13: Bangalore | D13: Avinash | E13: Avinash | F13: Rakshita | G13: Rakshita | H13: RE | I13: Thamilarasu | J13: Manufacturing Quality FTE | L13: Chennai | M13: 20.07.26 | N13: 400000 | O13: VHCPL/26-27/81 | P13: 33320 | Q13: 33320 | R13: 17.9.2026 | S13: PP | T13: PP | U13: Branch normalized: Banglaore → Bangalore
A14: 3502 | B14: Bengaluru | C14: Bangalore | D14: Avinash | E14: Avinash | F14: Rakshita | G14: Rakshita | H14: Royal Enfield | I14: Ganesh Ram | J14: Project & ME-Vehicle Assembly | L14: Chennai | M14: 31.08.26 | N14: 14,48,661 | O14: PI/26-27/79 | P14: 1,20,673.46 | Q14: 120673.46 | R14: 16.9.2026 | S14: IP | T14: IP | U14: Branch normalized: Bengaluru → Bangalore
A15: 3501 | B15: Bengaluru | C15: Bangalore | D15: Avinash | E15: Avinash | F15: Rakshita | G15: Rakshita | H15: Royal Enfield | I15: Indhuru D | J15: Project & ME-Machining | L15: Chennai | M15: 31.08.26 | N15: 6,16,121 | O15: PI/26-27/79 | P15: 51322.87 | Q15: 51322.87 | R15: 16.9.2026 | S15: IP | T15: IP | U15: Branch normalized: Bengaluru → Bangalore
A16: 3484 | B16: Banglaore | C16: Bangalore | D16: Avinash | E16: Avinash | F16: Rakshita | G16: Rakshita | H16: Royal Enfield | I16: Lakshmana Perumal.K | J16: Paint R&D | L16: Chennai | M16: 24.08.26 | N16: 16,07,143 | O16: PI/26-27/78 | P16: 1,33,875.01 | Q16: 133875.01 | R16: 16.9.2026 | S16: IP | T16: IP | U16: Branch normalized: Banglaore → Bangalore
A17: 3090 | B17: Bangalore | C17: Bangalore | D17: Avinash | E17: Avinash | F17: Rakshita | G17: Rakshita | H17: Shanthi Gear | I17: Senthil Murgun | J17: Head Finance | L17: Coimbatore | M17: 02.3.26 | N17: 3230898 | O17: VHCPL/25-26/107 | P17: 269133.8 | Q17: 269133.8 | R17: 05.03.2026 | S17: Payment Received | T17: Payment Received
A18: 3349 | B18: Bengaluru | C18: Bangalore | D18: Avinash | E18: Avinash | F18: shwetha | G18: Shwetha | H18: Mahindra AI | I18: Bhooyas Kapadia | J18: AI Engineer | L18: Mumbai | M18: 15.06.26 | N18: 2250000 | O18: VHCPL/26-27/36 | P18: 187425 | Q18: 187425 | R18: 8.7.2026 | S18: Payment Received | T18: Payment Received | U18: Branch normalized: Bengaluru → Bangalore; Recruiter normalized: shwetha → Shwetha
A19: 3434 | B19: Banglaore | C19: Bangalore | D19: Avinash | E19: Avinash | F19: Shwetha | G19: Shwetha | H19: RE | I19: Navya Satyanarayana. Gara | J19: FTE-ME-Machining | L19: Chennai | M19: 27.07.26 | N19: 350000 | O19: VHCPL/26-27/81 | P19: 35000 | Q19: 35000 | R19: 17.9.2026 | S19: PP | T19: PP | U19: Branch normalized: Banglaore → Bangalore
A20: 3485 | B20: Bengaluru | C20: Bangalore | D20: Avinash | E20: Avinash | F20: Shwetha | G20: Shwetha | H20: Royal Enfield | I20: Channabasava Hiremath | J20: Project & ME-Vehicle Assembly | L20: Chennai | M20: 24.08.26 | N20: 15,67,857 | O20: PI/26-27/78 | P20: 1,30,602.48 | Q20: 130602.48 | R20: 16.9.2026 | S20: IP | T20: IP | U20: Branch normalized: Bengaluru → Bangalore
A21: 3486 | B21: Banglaore | C21: Bangalore | D21: Avinash | E21: Avinash | F21: Shwetha | G21: Shwetha | H21: Royal Enfield | I21: Sanjay.S | J21: FTE-Product Enigneer | L21: Chennai | M21: 24.08.26 | N21: 4,50,000 | O21: PI/26-27/78 | P21: 37485 | Q21: 37485 | R21: 16.9.2026 | S21: IP | T21: IP | U21: Branch normalized: Banglaore → Bangalore
A22: 3537 | B22: Banglaore | C22: Bangalore | D22: Avinash | E22: Avinash | F22: Shwetha | G22: Shwetha | H22: Royal Enfield | I22: Santhoes kumar S | J22: Robotic Painting | L22: Chennai | M22: 07.09.26 | N22: 9,84,375 | O22: PI/26-27/80 | P22: 81998.43 | Q22: 81998.43 | R22: 16.9.2026 | S22: IP | T22: IP | U22: Branch normalized: Banglaore → Bangalore
A23: 3432 | B23: Bengaluru | C23: Bangalore | D23: Avinash | E23: Avinash | F23: Vedha | G23: Vedha | H23: RE | I23: Kushi Batta | J23: FTE Project & ME-Engine Assembly | L23: Chennai | M23: 27.07.26 | N23: 350000 | O23: VHCPL/26-27/81 | P23: 35000 | Q23: 35000 | R23: 17.9.2026 | S23: PP | T23: PP | U23: Branch normalized: Bengaluru → Bangalore
A24: 3487 | B24: Bengaluru | C24: Bangalore | D24: Avinash | E24: Avinash | F24: Vedha | G24: Vedha | H24: Royal Enfield | I24: Annamalai | J24: AM - SQA Sheet Metal | L24: Chennai | M24: 24.08.26 | N24: 7,18,214 | O24: PI/26-27/78 | P24: 59827.22 | Q24: 59827.22 | R24: 16.9.2026 | S24: IP | T24: IP | U24: Branch normalized: Bengaluru → Bangalore
A25: 3516 | B25: Banglaore | C25: Bangalore | D25: Avinash | E25: Avinash | F25: Vedha | G25: Vedha | H25: Royal Enfield | I25: Aravind E | J25: Maufacturing Quality | L25: Chennai | M25: 07.09.26 | N25: 4,50,000 | O25: PI/26-27/80 | P25: 37485 | Q25: 37485 | R25: 16.9.2026 | S25: IP | T25: IP | U25: Branch normalized: Banglaore → Bangalore
A26: 3450 | B26: Bangalore | C26: Bangalore | D26: Avinash | E26: Avinash | F26: Vedha | G26: Vedha | H26: Royal Enfield | I26: S. Dharani Kumar | J26: Paint | L26: Chennai | M26: 10.08.26 | N26: 12,50,000 | O26: PI/26-27/79 | P26: 1,04,125 | Q26: 104125 | R26: 16.9.2026 | S26: IP | T26: IP
A27: 3435 | B27: Bangalore | C27: Bangalore | D27: Avinash | E27: Avinash | F27: Visali | G27: Visali | H27: Miebach | I27: Twinkle | J27: HR | L27: Gurgaon | M27: 03.08.26 | N27: 1363000 | O27: VHCPL/26-27/68 | P27: 136300 | Q27: 136300 | R27: 3.9.2026 | S27: PP | T27: PP
A28: 3504 | B28: Bangalore | C28: Bangalore | D28: Avinash | E28: Avinash | F28: Visali | G28: Visali | H28: Royal Enfield | I28: Aravindsamy | J28: Store & Warehouse | L28: Chennai | M28: 31.08.26 | N28: 3,50,000 | O28: PI/26-27/80 | P28: 29155 | Q28: 29155 | R28: 16.9.2026 | S28: IP | T28: IP
A29: 3483 | B29: Bangalore | C29: Bangalore | D29: Avinash | E29: Avinash | F29: Visali | G29: Visali | H29: Royal Enfield | I29: Preethi S | J29: Store & Warehouse | L29: Chennai | M29: 24.08.26 | N29: 4,50,000 | O29: PI/26-27/80 | P29: 45000 | Q29: 45000 | R29: 16.9.2026 | S29: IP | T29: IP
A30: 3206 | B30: Bangalore | C30: Bangalore | D30: Haritha | E30: Haritha | F30: Shwetha | G30: Shwetha | H30: Miebach | I30: Nisha G Jammanakatti | J30: Hr & Admin | L30: Bangalore | M30: 13.04.26 | N30: 443000 | O30: VHCPL/26-27/13 | P30: 44300 | Q30: 44300 | R30: 15.05.26 | S30: Payment Received | T30: Payment Received
A31: 3375 | B31: Bengaluru | C31: Bangalore | D31: Jayadev | E31: Jayadev | F31: Jayadev | G31: Jayadev | H31: Borgwarner | I31: Sreeram PKJ | J31: Hardware Test Lead | L31: Bengaluru | M31: 06.07.26 | N31: 38,00,004 | O31: VHCPL/26-27/45 | P31: 3,73,517.59 | Q31: 373517.59 | R31: 22.7.2026 | S31: Payment Received | T31: Payment Received | U31: Branch normalized: Bengaluru → Bangalore
A32: 3463 | B32: Bengaluru | C32: Bangalore | D32: Jayadev | E32: Jayadev | F32: Navya | G32: Navya | H32: JSW | I32: Ajay Giri | J32: Solution /Data Architect | L32: Mumbai | M32: 17.08.26 | N32: 4380000 | O32: VHCPL/26-27/59 | P32: 438000 | Q32: 438000 | R32: 19.8.2026 | S32: PP | T32: PP | U32: Branch normalized: Bengaluru → Bangalore
A33: 3431 | B33: Bengaluru | C33: Bangalore | D33: Jayadev | E33: Jayadev | F33: Navya | G33: Navya | H33: JSW | I33: Ashish Bhavsar | J33: Product Management - Digitalization | L33: Mumbai | M33: 27.07.26 | N33: 28,61,000 | O33: VHCPL/26-27/49 | P33: 2,28,880 | Q33: 228880 | R33: 4.8.2026 | S33: PP | T33: PP | U33: Branch normalized: Bengaluru → Bangalore
A34: 3304 | B34: Bangalore | C34: Bangalore | D34: Jayadev | E34: Jayadev | F34: Navya | G34: Navya | H34: JSW | I34: Rupesh Kamble | J34: QA Engineer | L34: Mumbai | M34: 25.05.2026 | N34: 1550000 | O34: VHCPL/26-27/23 | P34: 124000 | Q34: 124000 | R34: 2.6.2026 | S34: Payment Received | T34: Payment Received
A35: 3091 | B35: Bangalore | C35: Bangalore | D35: Jayadev | E35: Jayadev | F35: Navya | G35: Navya | H35: JSW Energy | I35: Syed Iqbal | J35: Lead Data Scientist | L35: Mumbai | M35: 02.03.26 | N35: 7500000 | O35: VHCPL/25-26/111 | P35: 900000 | Q35: 900000 | R35: 10.03.2026 | S35: Payment Received | T35: Payment Received
A36: 3208 | B36: Bangalore | C36: Bangalore | D36: Jayadev | E36: Jayadev | F36: Rakshita | G36: Rakshita | H36: JSW Energy | I36: Souvik Ghosh | J36: DGM - Digital Lead | L36: Mumbai | M36: 20.04.26 | N36: 5900000 | O36: VHCPL/26-27/06 | P36: 590000 | Q36: 590000 | R36: 22.04.2026 | S36: Payment Received | T36: Payment Received
A37: 3303 | B37: Bangalore | C37: Bangalore | D37: Jayadev | E37: Jayadev | F37: Shwetha | G37: Shwetha | H37: Borgwarner | I37: Arnold Matthew | J37: ALM Tool Engineer | L37: Bangalore | M37: 07.05.26 | N37: 1100000 | O37: VHCPL/26-27/17 | P37: 87465 | Q37: 87465 | R37: 28.5.2026 | S37: Payment Received | T37: Payment Received
A38: 3515 | B38: Bangalore | C38: Bangalore | D38: Jayadev | E38: Jayadev | F38: Shwetha | G38: Shwetha | H38: Borgwarner | I38: Sanjay Gowda | J38: SIL Software Development Lead Engineer | L38: Bangalore | M38: 03.09.26 | N38: 2200000 | O38: VHCPL/26-27/70 | P38: 183260 | Q38: 183260 | R38: 8.9.2026 | S38: PP | T38: PP
A39: 3302 | B39: Bangalore | C39: Bangalore | D39: Navya | E39: Navya | F39: Avinash | G39: Avinash | H39: SAR Group | I39: Manjunath MP | J39: Manager BD | L39: Bangalore | M39: 04.05.26 | N39: 2846496 | O39: VHCPL/26-27/15 | P39: 237113.12 | Q39: 237113.12 | R39: 27.05.2026 | S39: Payment Received | T39: Payment Received
A40: 3308 | B40: Bangalore | C40: Bangalore | D40: Navya | E40: Navya | F40: Shwetha | G40: Shwetha | H40: SAR | I40: Nikitha SM | J40: Embedded Fimware Engineer | L40: Bangalore | M40: 08.06.26 | N40: 1048000 | O40: VHCPL/26-27/27 | P40: 87298.4 | Q40: 87298.4 | R40: 12.6.2026 | S40: Payment Received | T40: Payment Received
A41: 3449 | B41: Bengaluru | C41: Bangalore | D41: Rakshita | E41: Rakshita | F41: Rakshita | G41: Rakshita | H41: Sulzer | I41: Ashok Kumar Bokkasm | J41: Regional Sales Manager | L41: Chennai | M41: 10.08.26 | N41: 2100000 | O41: VHCPL/26-27/58 | P41: 1,74,930 | Q41: 174930 | R41: 19.8.2026 | S41: PP | T41: PP | U41: Branch normalized: Bengaluru → Bangalore
A42: 3448 | B42: Bangalore | C42: Bangalore | D42: Rakshita | E42: Rakshita | F42: Rakshita | G42: Rakshita | H42: Sulzer | I42: Sandeep Kumar | J42: Field Service Engineer - Turbo Services | L42: Vadodara | M42: 05.08.26 | N42: 1350000 | O42: VHCPL/26-27/58 | P42: 1,12,455 | Q42: 112455 | R42: 19.8.2026 | S42: PP | T42: PP
A43: 3059 | B43: Bangalore | C43: Bangalore | D43: Rakshita | E43: Rakshita | F43: Shwetha | G43: Shwetha | H43: Di Aero Pvt. Ltd. | I43: Rekha Kumari | J43: Senior Executive Admin | L43: Bangalore | M43: 09.02.26 | N43: 600000 | O43: VHCPL/25-26/104 | P43: 60000 | Q43: 60000 | R43: 23.02.2026 | S43: Payment Received | T43: Payment Received
A44: 3077 | B44: Bangalore | C44: Bangalore | D44: Rakshitha | E44: Rakshitha | F44: Shwetha | G44: Shwetha | H44: Diaero | I44: Santosh Kumar Mishra | J44: Senior Executive Accounts | L44: Noida | M44: 17.02.26 | N44: 950000 | O44: VHCPL/25-26/113 | P44: 79135 | Q44: 79135 | R44: 13.03.2026 | S44: Payment Received | T44: Payment Received
A45: 3429 | B45: Bangalore | C45: Bangalore | D45: Vedha | E45: Vedha | F45: Rakshita | G45: Rakshita | H45: VECS | I45: Mahesh B | J45: Embedded Firmware Developer | L45: Bangalore | M45: 22.07.26 | N45: 900000 | O45: VHC/26-27/80 | P45: 74970 | Q45: 74970 | R45: 6.8.2026 | S45: Payment Received | T45: Payment Received
A46: 3361 | B46: Bangalore | C46: Bangalore | D46: Vedha | E46: Vedha | F46: Vedha | G46: Vedha | H46: VECS | I46: Gurunath | J46: Embedded Developer | L46: Bangalore | M46: 18.06.26 | N46: 700000 | O46: VHC/26-27/71 | P46: 58310 | Q46: 58310 | R46: 31.7.2026 | S46: Payment Received | T46: Payment Received
A47: 3464 | B47: Bangalore | C47: Bangalore | D47: Visali | E47: Visali | F47: Vedha | G47: Vedha | H47: Shanti Gears | I47: Krishna Kumar | J47: Asst. Manager -BD- Defence | L47: Coimbatore | M47: 17.08.26 | N47: 12,47,160 | O47: VHCPL/26-27/67 | P47: 103888.42 | Q47: 103888.42 | R47: 2.9.2026 | S47: PP | T47: PP
A48: 3461 | B48: Banglaore | C48: Bangalore | D48: Vishali | E48: Vishali | F48: Vedha | G48: Vedha | H48: Shanti Gears | I48: N. Karthikeyan | J48: Application Engineer - Construction Equipment | L48: Coimbatore | M48: 10.08.26 | N48: 8,88,000 | O48: VHCPL/26-27/67 | P48: 73970.4 | Q48: 73970.4 | R48: 2.9.2026 | S48: PP | T48: PP | U48: Branch normalized: Banglaore → Bangalore
A49: 3478 | B49: Delhi | C49: Delhi | D49: Manorma | E49: Manorma | F49: Bhumika | G49: Bhumika | H49: Escorts Kubota Finance | I49: Saloni Soni | J49: Lead -IT (Senior Manager / Chief Manager) | L49: Faridabad | M49: 12.08.26 | N49: 4450000 | P49: 400000 | Q49: 400000 | S49: IP | T49: IP
A50: 3287 | B50: Delhi | C50: Delhi | D50: Manorma | E50: Manorma | F50: Bhumika | G50: Bhumika | H50: Hyundai Mobis | I50: Umesh Patil | J50: Global OE Sales – GM Level | L50: Gurgaon | M50: 12.05.26 | N50: 9720000 | O50: VHCPL/26-27/53 | P50: 9,72,000 | Q50: 972000 | R50: 13.8.2026 | S50: PP | T50: PP
A51: 3184 | B51: Delhi | C51: Delhi | D51: Manorma | E51: Manorma | F51: Bhumika | G51: Bhumika | H51: JKYMS | I51: Amit Sharma | J51: Team Member – HR Operations | L51: Gurgaon | M51: 02.04.26 | N51: 1250004 | O51: VHC/26-27/68 | P51: 87500.28 | Q51: 87500.28 | R51: 29.7.2026 | S51: Payment Received | T51: Payment Received
A52: 3173 | B52: Delhi | C52: Delhi | D52: Manorma | E52: Manorma | F52: Bhumika | G52: Bhumika | H52: JKYMS | I52: Raushan Kumar Jha | J52: Team Lead - Accounts payable | L52: Gurgaon | M52: 30.03.26 | N52: 1565004 | O52: VHC/26-27/67 | P52: 109550.28 | Q52: 109550.28 | R52: 29.7.2026 | S52: Payment Received | T52: Payment Received
A53: 3140 | B53: Delhi | C53: Delhi | D53: Manorma | E53: Manorma | F53: Bhumika | G53: Bhumika | H53: JKYMS | I53: Sandeep Kumar Narwal | J53: Senior Analyst - Accounts payable | L53: Gurgaon | M53: 16.03.26 | N53: 850000 | O53: VHC/25-26/155 | P53: 59500 | Q53: 59500 | R53: 20.03.2026 | S53: Payment Received | T53: Payment Received
A54: 3514 | B54: Delhi | C54: Delhi | D54: Manorma | E54: Manorma | F54: Bhumika | G54: Bhumika | H54: JSW Energy | I54: Praduman Pratap Singh | J54: AGM - Transmission Line | L54: Jharsuguda | M54: 25.08.26 | N54: 4500000 | O54: VHCPL/26-27/75 | P54: 4,50,000 | Q54: 450000 | R54: 11.9.2026 | S54: PP | T54: PP
A55: 3065 | B55: Delhi | C55: Delhi | D55: Manorma | E55: Manorma | F55: Bhumika | G55: Bhumika | H55: JSW Energy | I55: Riya Jain | J55: Deputy Manager - Direct Taxation | L55: Mumbai | M55: 11.02.26 | N55: 1650000 | O55: VHCPL/25-26/106 | P55: 132000 | Q55: 132000 | R55: 27.02.2026 | S55: Payment Received | T55: Payment Received
A56: 3219 | B56: Delhi | C56: Delhi | D56: Manorma | E56: Manorma | F56: Bhumika | G56: Bhumika | H56: Mitsubishi | I56: Sandeep Kanyal | J56: Manager - JSOX | L56: Gurgaon | M56: 13.04.26 | N56: 3200004 | O56: VHC/26-27/09 | P56: 320000.4 | Q56: 320000.4 | R56: 22.04.2026 | S56: Payment Received | T56: Payment Received
A57: 3138 | B57: Delhi | C57: Delhi | D57: Manorma | E57: Manorma | F57: Bhumika | G57: Bhumika | H57: Suzuki | I57: S M Shanawaz Mujawar | J57: Leader - Crash Analysis | L57: Pune | M57: 16.03.26 | N57: 2300000 | O57: VHCPL/25-26/116 | P57: 191590 | Q57: 191590 | R57: 24.03.2026 | S57: Payment Received | T57: Payment Received
A58: 3271 | B58: Delhi | C58: Delhi | D58: Manorma | E58: Manorma | F58: Kavita | G58: Kavita | H58: Hero Motocorp | I58: Jatin Sharma | J58: SCM – Sheet Metal | L58: Gurugram | M58: 30.6.2026 | N58: 1079270 | O58: VHCPL/26-27/31 | P58: 89903.19 | Q58: 89903.19 | R58: 25.6.2026 | S58: Payment Received | T58: Payment Received
A59: 3270 | B59: Delhi | C59: Delhi | D59: Manorma | E59: Manorma | F59: Kavita | G59: Kavita | H59: Hero Motocorp | I59: Nikhil Paliwal | J59: Program Manager- Digital | L59: UV- Gurugram | M59: 30.6.2026 | N59: 2046351 | O59: VHCPL/26-27/31 | P59: 1,70,461.04 | Q59: 170461.04 | R59: 25.6.2026 | S59: Payment Received | T59: Payment Received
A60: 3061 | B60: Delhi | C60: Delhi | D60: Manorma | E60: Manorma | F60: Kavita | G60: Kavita | H60: Hero Motocorp | I60: Piyush Purohit | J60: SCM E4 | L60: Neemrana | M60: 02.02.26 | N60: 1203802 | O60: VHCPL./25-26/112 | P60: 100276.71 | Q60: 100276.71 | R60: 11.03.2026 | S60: Payment Received | T60: Payment Received
A61: 3481 | B61: Delhi | C61: Delhi | D61: Manorma | E61: Manorma | F61: Kavita | G61: Kavita | H61: Hero Motocorp | I61: Rakesh R | J61: Buyer- Supply Chain Operations | L61: Tirupati | M61: 17.08.26 | N61: 1442088 | O61: VHCPL/26-27/72 | P61: 1,20,125.93 | Q61: 120125.93 | R61: 8.9.2026 | S61: PP | T61: PP
A62: 3247 | B62: Delhi | C62: Delhi | D62: Manorma | E62: Manorma | F62: Kavita | G62: Kavita | H62: Hero Motocorp | I62: Saurabh Sharma | J62: E4 - SCM | L62: Neemrana | M62: 30.6.2026 | N62: 813604 | O62: VHCPL/26-27/31 | P62: 67773.21 | Q62: 67773.21 | R62: 25.6.2026 | S62: Payment Received | T62: Payment Received
A63: 3133 | B63: Delhi | C63: Delhi | D63: Manorma | E63: Manorma | F63: Kavita | G63: Kavita | H63: Hero Motocorp | I63: Sumitabh Paul | J63: E4 - Buyer - Polymer | L63: Gurugram | M63: 09.03.26 | N63: 1120781 | O63: VHCPL/25-26/117 | P63: 93361.057 | Q63: 93361.057 | R63: 30.03.2026 | S63: Payment Received | T63: Payment Received
A64: 3023 | B64: Delhi | C64: Delhi | D64: Manorma | E64: Manorma | F64: Kavita | G64: Kavita | H64: Hero Motocorp | I64: Suprajeet Lenka | J64: E4 | L64: Neemrana | M64: 05.01.26 | N64: 1079270 | O64: VHCPL/25-26/100 | P64: 89903.191 | Q64: 89903.191 | R64: 09.02.2026 | S64: Payment Received | T64: Payment Received
A65: 3534 | B65: Delhi | C65: Delhi | D65: Manorma | E65: Manorma | F65: Kavita | G65: Kavita | H65: Hero Motocorp | I65: Vaishnavi Tripathi | J65: ER- Contingent Cell | L65: Neemrana | M65: 07.09.26 | N65: 1214000 | P65: 72000 | Q65: 72000 | S65: IP | T65: IP
A66: 3314 | B66: Delhi | C66: Delhi | D66: Manorma | E66: Manorma | F66: Kavita | G66: Kavita | H66: Hero Motocorp | I66: Vivek Gaur | J66: Buyer Supply Chain | L66: Gurugram | M66: 30.6.2026 | N66: 1328333 | O66: VHCPL/26-27/31 | P66: 1,10,650.14 | Q66: 110650.14 | R66: 25.6.2026 | S66: Payment Received | T66: Payment Received
A67: 3166 | B67: Delhi | C67: Delhi | D67: Manorma | E67: Manorma | F67: Kavita | G67: Kavita | H67: JKYMS | I67: Meena | J67: Accounts Receivables | L67: Gurgaon | M67: 23.03.26 | N67: 300000 | O67: VHC/26-27/67 | P67: 25000 | Q67: 25000 | R67: 29.7.2026 | S67: Payment Received | T67: Payment Received
A68: 3135 | B68: Delhi | C68: Delhi | D68: Manorma | E68: Manorma | F68: Kavita | G68: Kavita | H68: JKYMS | I68: Navdeep | J68: Payable | L68: Gurugram | M68: 09.03.26 | N68: 480000 | O68: VHC/25-26/155 | P68: 25000 | Q68: 25000 | R68: 20.03.2026 | S68: Payment Received | T68: Payment Received
A69: 3115 | B69: Delhi | C69: Delhi | D69: Manorma | E69: Manorma | F69: Kavita | G69: Kavita | H69: JKYMS | I69: Rahul Kumar | J69: Receivable | L69: Gurugram | M69: 02.03.26 | N69: 350000 | O69: VHC/25-26/154 | P69: 25000 | Q69: 25000 | R69: 20.03.2026 | S69: Payment Received | T69: Payment Received
A70: 3134 | B70: Delhi | C70: Delhi | D70: Manorma | E70: Manorma | F70: Kavita | G70: Kavita | H70: JKYMS | I70: Sushil kumar | J70: Payable | L70: Gurugram | M70: 09.03.26 | N70: 600000 | O70: VHC/25-26/155 | P70: 42000 | Q70: 42000 | R70: 20.03.2026 | S70: Payment Received | T70: Payment Received
A71: 3177 | B71: Delhi | C71: Delhi | D71: Manorma | E71: Manorma | F71: Kavita | G71: Kavita | H71: JKYMS | I71: Yaseen Saifi | J71: Payable | L71: Gurgaon | M71: 30.03.26 | N71: 545004 | O71: VHC/26-27/67 | P71: 38150.28 | Q71: 38150.28 | R71: 29.7.2026 | S71: Payment Received | T71: Payment Received
A72: 3322 | B72: Delhi | C72: Delhi | D72: Manorma | E72: Manorma | F72: Kavita | G72: Kavita | H72: MG motor | I72: Raksha Patel | J72: Warehouse Operations | L72: Halol | M72: 01.06.26 | N72: 650007 | O72: VHCPL/26-27/22 | P72: 67145.72 | Q72: 67145.72 | R72: 1.6.2026 | S72: Payment Received | T72: Payment Received
A73: 3331 | B73: Delhi | C73: Delhi | D73: Manorma | E73: Manorma | F73: Kavita | G73: Kavita | H73: Treadwell | I73: Chirayu Chavda | J73: Project Manager | L73: Ahmedabad | M73: 09.06.26 | N73: 1310000 | O73: VHCPL/26-27/34 | P73: 131000 | Q73: 131000 | R73: 30.6.2026 | S73: Payment Received | T73: Payment Received
A74: 3374 | B74: Delhi | C74: Delhi | D74: Manorma | E74: Manorma | F74: Kavita | G74: Kavita | H74: Treadwell | I74: Hari Krishnan | J74: Project Manager | L74: Ahmedabad | M74: 30.06.26 | N74: 1250000 | O74: VHCPL/26-27/34 | P74: 1,25,000 | Q74: 125000 | R74: 30.6.2026 | S74: Payment Received | T74: Payment Received
A75: 3513 | B75: Delhi | C75: Delhi | D75: Manorma | E75: Manorma | F75: Khushi Makkar | G75: Khushi Makkar | H75: Hero Moto Corp | I75: Shantanu Ramakant Mokashi | J75: Territory Sales Officer (Offroll) | L75: Aurangabad | M75: 24.08.26 | N75: 546456 | P75: 30000 | Q75: 30000 | S75: IP | T75: IP
A76: 3372 | B76: Delhi | C76: Delhi | D76: Manorma | E76: Manorma | F76: Khushi Makkar | G76: Khushi Makkar | H76: Mitsubishi | I76: Sagar Borde | J76: Office Administrator | L76: Ahmedabad | M76: 22.06.26 | N76: 4,91,100 | O76: VHC/26-27/61 | P76: 40908.63 | Q76: 40908.63 | R76: 9.7.2026 | S76: Payment Received | T76: Payment Received
A77: 3389 | B77: Delhi | C77: Delhi | D77: Manorma | E77: Manorma | F77: Khushi Makkar | G77: Khushi Makkar | H77: Mitsubishi | I77: Tushar Vats | J77: Office Administrator | L77: Gurgaon | M77: 06.07.26 | N77: 6,00,000 | O77: VHC/26-27/61 | P77: 49980 | Q77: 49980 | R77: 9.7.2026 | S77: Payment Received | T77: Payment Received
A78: 3477 | B78: Delhi | C78: Delhi | D78: Manorma | E78: Manorma | F78: Khushi Makkar | G78: Khushi Makkar | H78: Panasonic Corporate | I78: Soumyak Das | J78: Assistant Manager - Sales | L78: Bhubaneshwar | M78: 10.08.26 | N78: 1128005 | O78: VHC/26-27/93 | P78: 93962.81 | Q78: 93962.81 | R78: 11.9.2026 | S78: IP | T78: IP
A79: 3445 | B79: Delhi | C79: Delhi | D79: Manorma | E79: Manorma | F79: Khushi Makkar | G79: Khushi Makkar | H79: Tufropes | I79: Bishal Das | J79: Sr. Executive - Sales | L79: Guwahati | M79: 03.08.26 | N79: 655000 | O79: VHCPL/26-27/51 | P79: 54561.5 | Q79: 54561.5 | R79: 10.8.2026 | S79: Payment Received | T79: Payment Received
A80: 3183 | B80: Delhi | C80: Delhi | D80: Manorma | E80: Manorma | F80: Manas | G80: Manas | H80: JKYMS | I80: Gagan Wadhavan | J80: AR Trainee | L80: Gurgaon | M80: 02.04.26 | N80: 300000 | O80: VHC/26-27/68 | P80: 25000 | Q80: 25000 | R80: 29.7.2026 | S80: Payment Received | T80: Payment Received
A81: 3446 | B81: Delhi | C81: Delhi | D81: Manorma | E81: Manorma | F81: Manas | G81: Manas | H81: MG Motors | I81: Deepak Chander | J81: Junior Engineer – Press Shop (Die Maintenance) | L81: Halol | M81: 03.08.26 | N81: 5,50,012 | O81: VHCPL/26-27/52 | P81: 45815.99 | Q81: 45815.99 | R81: 10.8.2026 | S81: Payment Received | T81: Payment Received
A82: 3351 | B82: Delhi | C82: Delhi | D82: Manorma | E82: Manorma | F82: Manas | G82: Manas | H82: MG Motors | I82: Kaustubh Kumar Naik | J82: Spare Parts Engineer – Aftersales Engineering | L82: Halol | M82: 15.06.26 | N82: 650007 | O82: VHCPL/26-27/28 | P82: 54145.58 | Q82: 54145.58 | R82: 22.6.2026 | S82: Payment Received | T82: Payment Received
A83: 3277 | B83: Delhi | C83: Delhi | D83: Manorma | E83: Manorma | F83: Manas | G83: Manas | H83: MG Motors | I83: Sonu Tilak | J83: Production-Body Shop | L83: Halol | M83: 11.05.26 | N83: 525001 | O83: VHCPL/26-27/14 | P83: 43732.583 | Q83: 43732.583 | R83: 18.05.2026 | S83: Payment Received | T83: Payment Received
A84: 3131 | B84: Delhi | C84: Delhi | D84: Manorma | E84: Manorma | F84: Maneet | G84: Maneet | H84: Mitsubishi | I84: Abhay Kumar Pankaj | J84: BMS Engineer | L84: Gurgaon | M84: 09.03.26 | N84: 2924267 | O84: VHC/25-26/150 | P84: 292426.7 | Q84: 292426.7 | R84: 17.03.2026 | S84: Payment Received | T84: Payment Received
A85: 3441 | B85: Delhi | C85: Delhi | D85: Manorma | E85: Manorma | F85: Navya | G85: Navya | H85: JKYMS | I85: Arun Sharma | J85: Sr Analyst - AP | L85: Gurgaon | M85: 31.07.26 | N85: 915000 | O85: VHC/26-27/78 | P85: 64050 | Q85: 64050 | R85: 3.8.2026 | S85: Payment Received | T85: Payment Received
A86: 3109 | B86: Delhi | C86: Delhi | D86: Manorma | E86: Manorma | F86: Navya | G86: Navya | H86: JKYMS | I86: Ayushi Parashar | J86: SR Analyst - AR | L86: Gurgaon | M86: 02.03.26 | N86: 1200000 | O86: VHC/25-26/154 | P86: 84000 | Q86: 84000 | R86: 20.03.2026 | S86: Payment Received | T86: Payment Received
A87: 3188 | B87: Delhi | C87: Delhi | D87: Manorma | E87: Manorma | F87: Navya | G87: Navya | H87: JKYMS | I87: Deepak Goyal | J87: TL – R2R | L87: Gurgaon | M87: 02.04.26 | N87: 2325000 | O87: VHC/26-27/68 | P87: 162750 | Q87: 162750 | R87: 29.7.2026 | S87: Payment Received | T87: Payment Received
A88: 3286 | B88: Delhi | C88: Delhi | D88: Manorma | E88: Manorma | F88: Navya | G88: Navya | H88: JKYMS | I88: Gaurav Bhayana | J88: Sr Analyst R2R | L88: Gurgaon | M88: 11.05.26 | N88: 1700000 | O88: VHC/26-27/39 | P88: 42000 | Q88: 42000 | R88: 27.05.2026 | S88: credit note | T88: Credit Note
A89: 3252 | B89: Delhi | C89: Delhi | D89: Manorma | E89: Manorma | F89: Navya | G89: Navya | H89: JKYMS | I89: Gopal Das | J89: Admin (Team Member) | L89: Gurgaon | M89: 27.04.26 | N89: 675000 | O89: VHC/26-27/30 | P89: 47250 | Q89: 47250 | R89: 13.05.2026 | S89: Payment Received | T89: Payment Received
A90: 3282 | B90: Delhi | C90: Delhi | D90: Manorma | E90: Manorma | F90: Navya | G90: Navya | H90: JKYMS | I90: Hari Narayan | J90: TL - AR | L90: Gurgaon | M90: 11.05.26 | N90: 1391000 | O90: VHC/26-27/39 | P90: 97370 | Q90: 97370 | R90: 27.05.2026 | S90: Payment Received | T90: Payment Received
A91: 3373 | B91: Delhi | C91: Delhi | D91: Manorma | E91: Manorma | F91: Navya | G91: Navya | H91: JKYMS | I91: Himanshu Chauhan | J91: AR - Analyst | L91: Gurgaon | M91: 25.06.26 | N91: 455004 | O91: VHC/26-27/54 | P91: 25000 | Q91: 25000 | R91: 2.7.2026 | S91: Payment Received | T91: Payment Received
A92: 3110 | B92: Delhi | C92: Delhi | D92: Manorma | E92: Manorma | F92: Navya | G92: Navya | H92: JKYMS | I92: Himanshu Jain | J92: TL – R2R | L92: Gurgaon | M92: 02.03.26 | N92: 2400000 | O92: VHC/25-26/154 | P92: 168000 | Q92: 168000 | R92: 20.03.2026 | S92: Payment Received | T92: Payment Received
A93: 3186 | B93: Delhi | C93: Delhi | D93: Manorma | E93: Manorma | F93: Navya | G93: Navya | H93: JKYMS | I93: Manish Kumar | J93: R2R | L93: Gurgaon | M93: 02.04.26 | N93: 625008 | O93: VHC/26-27/68 | P93: 43750.56 | Q93: 43750.56 | R93: 29.7.2026 | S93: Payment Received | T93: Payment Received
... A95: 3254 | B95: Delhi | C95: Delhi | D95: Manorma | E95: Manorma | F95: Navya | G95: Navya | H95: JKYMS | I95: Nitish Verma | J95: Payable | L95: Gurgaon | M95: 28.04.26 | N95: 500000 | O95: VHC/26-27/30 | P95: 44100 | Q95: 44100 | R95: 13.05.2026 | S95: Payment Received | T95: Payment Received
A96: 3217 | B96: Delhi | C96: Delhi | D96: Manorma | E96: Manorma | F96: Navya | G96: Navya | H96: JKYMS | I96: Prakash Parashar | J96: SR Analyst R2R | L96: Gurgaon | M96: 13.04.26 | N96: 924996 | P96: 0 | Q96: 0 | S96: Backout | T96: Backout
A97: 3144 | B97: Delhi | C97: Delhi | D97: Manorma | E97: Manorma | F97: Navya | G97: Navya | H97: JKYMS | I97: Prince verma | J97: Receivable | L97: Gurugram | M97: 16.03.26 | N97: 405000 | O97: VHC/25-26/155 | P97: 25000 | Q97: 25000 | R97: 20.03.2026 | S97: Payment Received | T97: Payment Received
A98: 3141 | B98: Delhi | C98: Delhi | D98: Manorma | E98: Manorma | F98: Navya | G98: Navya | H98: JKYMS | I98: Rajan Kumar | J98: Payable | L98: Gurugram | M98: 16.03.26 | N98: 600000 | O98: VHC/25-26/155 | P98: 42000 | Q98: 42000 | R98: 20.03.2026 | S98: Payment Received | T98: Payment Received
A99: 3165 | B99: Delhi | C99: Delhi | D99: Manorma | E99: Manorma | F99: Navya | G99: Navya | H99: JKYMS | I99: Rajan Mishra | J99: SR Analyst - AP | L99: Gurgaon | M99: 20.03.26 | N99: 650000 | O99: VHC/25-26/155 | P99: 45500 | Q99: 45500 | R99: 20.03.2026 | S99: Payment Received | T99: Payment Received
A100: 3250 | B100: Delhi | C100: Delhi | D100: Manorma | E100: Manorma | F100: Navya | G100: Navya | H100: JKYMS | I100: Ruchika Verma | J100: Analyst AR | L100: Gurgaon | M100: 20.04.26 | N100: 550000 | O100: VHC/26-27/69 | P100: 38500 | Q100: 38500 | R100: 29.7.2026 | S100: Payment Received | T100: Payment Received
A101: 3444 | B101: Delhi | C101: Delhi | D101: Manorma | E101: Manorma | F101: Navya | G101: Navya | H101: JKYMS | I101: Rupesh Kumar Jha | J101: Sr Analyst - AP | L101: Gurgaon | M101: 03.08.26 | N101: 856000 | O101: VHC/26-27/81 | P101: 59920 | Q101: 59920 | R101: 10.8.2026 | S101: Payment Received | T101: Payment Received
...

Sheet Data Quality
A1: Source Row | B1: S.No | C1: Branch | D1: Account Manager | E1: Recruiter | F1: Organization | G1: Candidate | H1: Billing Amount | I1: Payment Status | J1: Review Note | L1: Standardization / Review Item | M1: Count
A2: 26 | B2: 3312 | C2: Faridabad | D2: Bikash Das | E2: Madhuri | F2: JK Tilemaxx | G2: Shubam Gupta | I2: Backout | J2: Billing Amount blank | L2: Rows retained (S.No present) | M2: 527
A3: 42 | B3: 3167 | C3: Delhi | D3: Manorma | E3: Unassigned / Blank Recruiter | F3: Defsys | G3: Ajay Kumar Biswas | H3: 37485 | I3: Payment Received | J3: Recruiter blank; grouped as Unassigned / Blank Recruiter | L3: Trailing total-only rows excluded | M3: 2
A4: 128 | B4: 3026 | C4: Delhi | D4: Manorma | E4: Unassigned / Blank Recruiter | F4: Panasonic Corporate | G4: Malakkaran Aneesh Appukuttan | H4: 107623.6 | I4: Payment Received | J4: Recruiter blank; grouped as Unassigned / Blank Recruiter | L4: Bengaluru → Bangalore | M4: 13
A5: 173 | B5: 3395 | C5: Delhi | D5: Manorma | E5: Unassigned / Blank Recruiter | F5: JSW Energy | G5: Khushhal Agarwal | H5: 1,52,000 | I5: PP | J5: Recruiter blank; grouped as Unassigned / Blank Recruiter | L5: Banglaore → Bangalore | M5: 8
A6: 175 | B6: 3325 | C6: Delhi | D6: Manorma | E6: Unassigned / Blank Recruiter | F6: JKYMS | G6: Harpreet Singh | H6: 1,15,220.28 | I6: Payment Received | J6: Recruiter blank; grouped as Unassigned / Blank Recruiter | L6: Lowercase PP → PP | M6: 1
A7: 176 | B7: 3326 | C7: Delhi | D7: Manorma | E7: Unassigned / Blank Recruiter | F7: JKYMS | G7: Pankaj Vashisth | H7: 1,19,665.56 | I7: Payment Received | J7: Recruiter blank; grouped as Unassigned / Blank Recruiter | L7: Blank recruiter | M7: 9
A8: 178 | B8: 3329 | C8: Delhi | D8: Manorma | E8: Unassigned / Blank Recruiter | F8: MG Motor | G8: Naresh Singh | H8: 43316.91 | I8: Payment Received | J8: Recruiter blank; grouped as Unassigned / Blank Recruiter | L8: Unmapped payment status | M8: 1
A9: 204 | B9: 3274 | C9: Delhi | D9: Manorma | E9: Stuti | F9: JKYMS | G9: Mukesh Thaakur | H9: 46094 | I9: FVHC/26-27/39 | J9: Payment Status needs review | L9: Blank billing amount | M9: 4
A10: 219 | B10: 3269 | C10: Delhi | D10: Manorma | E10: Unassigned / Blank Recruiter | F10: Defsys | G10: Alok Singh | H10: 36985.2 | I10: Payment Received | J10: Recruiter blank; grouped as Unassigned / Blank Recruiter
A11: 241 | B11: 3108 | C11: Delhi | D11: Manorma | E11: Unassigned / Blank Recruiter | F11: Defsys | G11: Parwinder Singh | H11: 50979.6 | I11: Payment Received | J11: Recruiter blank; grouped as Unassigned / Blank Recruiter
A12: 329 | B12: 3439 | C12: Faridabad | D12: Bikash Das | E12: Unassigned / Blank Recruiter | F12: Tylo | G12: Shankara Gouda V Patil | H12: 45500.28 | I12: Payment Received | J12: Recruiter blank; grouped as Unassigned / Blank Recruiter
A13: 514 | B13: 3028 | C13: Gurgaon | D13: Rohit Yadav | E13: Gaurav | F13: VECV Sales | G13: Anurag Mishra | I13: Backout | J13: Billing Amount blank
A14: 525 | B14: 3014 | C14: Faridabad | D14: Bikash Das | E14: Indu | F14: JK Cement | G14: Nikhil Pandya | I14: Payment Received | J14: Billing Amount blank
A15: 528 | B15: 3013 | C15: Faridabad | D15: Bikash Das | E15: Bikash Das | F15: JK Cement | G15: Manish Shukla | I15: Payment Received | J15: Billing Amount blank
